<?xml version="1.0" encoding="UTF-8"?>
<LanguageData>
  
  <!-- EN: collapse dodged -->
  <CollapseDodged.label>崩落の回避</CollapseDodged.label>
  <!-- EN:
    <li>tale_noun->[PAWN_nameDef] dodging a cave-in</li>
    <li>tale_noun->[PAWN_nameDef] nearly crushed by falling objects</li>
    <li>image->[PAWN_nameFull] leaping away from a collapse of debris [circumstance_group]</li>
    <li>image->[PAWN_nameFull] narrowly avoiding a cave-in [circumstance_group]</li>
    <li>image->[PAWN_nameFull] avoiding a falling ceiling [circumstance_group]</li>
    <li>image->[PAWN_nameFull] avoiding certain death by a falling rock [circumstance_group]</li>
    <li>circumstance_phrase->that vanishes behind a curtain of debris and dust</li>
    <li>circumstance_phrase->that pulverizes everything beneath it</li>
    <li>circumstance_phrase->which impacts with incredible force</li>
    <li>desc_sentence->[PAWN_pronoun] is sweating with exertion.</li>
    <li>desc_sentence->[PAWN_pronoun] appears to be terrified.</li>
    <li>desc_sentence->[PAWN_pronoun] is scratched and bleeding.</li>
    <li>desc_sentence->[PAWN_pronoun] has lost [PAWN_possessive] balance.</li>
  -->
  <CollapseDodged.rulePack.rulesStrings>
    <li>tale_noun->崩落事故から身を躱す[PAWN_nameDef]</li>
    <li>tale_noun->付近で落下物が粉々になる[PAWN_nameDef]</li>
    <li>image->[circumstance_group]崩落してきた岩のかけらを飛び跳ねて避ける[PAWN_nameDef]</li>
    <li>image->[circumstance_group]なんとか崩落事故を避ける[PAWN_nameDef]</li>
    <li>image->[circumstance_group]落ちてきた天井を避ける[PAWN_nameDef]</li>
    <li>image->[circumstance_group]落石で死ぬところを免れる[PAWN_nameDef]</li>
    <li>circumstance_phrase->一面の塵と粉塵の中に消えるよう</li>
    <li>circumstance_phrase->近くにある物全てを粉々にする程の規模の中</li>
    <li>circumstance_phrase->尋常では無い力による衝撃で起きた中</li>
    <li>desc_sentence->[PAWN_pronoun]は力を出して汗をかいている.</li>
    <li>desc_sentence->[PAWN_pronoun]はゾッとしているように見える.</li>
    <li>desc_sentence->[PAWN_pronoun]は擦り傷を負い血を流している.</li>
    <li>desc_sentence->[PAWN_pronoun]はバランスを失っている.</li>
  </CollapseDodged.rulePack.rulesStrings>
  
  <!-- EN: launched ship -->
  <LaunchedShip.label>宇宙船の発進</LaunchedShip.label>
  <!-- EN:
    <li>tale_noun->[PAWN_nameDef] escaping the planet</li>
    <li>tale_noun->[PAWN_nameDef] taking off in a spaceship</li>
    <li>image->[PAWN_nameFull] being launched towards the stars [circumstance_group]</li>
    <li>image->[PAWN_nameFull] racing towards the heavens [circumstance_group]</li>
    <li>image->[PAWN_nameFull] accelerating to escape velocity [circumstance_group]</li>
    <li>image->[PAWN_nameFull] piloting a rocket [circumstance_group]</li>
    <li>circumstance_phrase->in front of a [TerrainFeature]</li>
    <li>circumstance_phrase->with incredible force</li>
    <li>circumstance_phrase->in a plume of dust and rocks</li>
    <li>circumstance_phrase->with rockets firing dramatically</li>
    <li>circumstance_phrase->in a precision takeoff</li>
    <li>desc_sentence->[PAWN_pronoun] is concentrating intently on the controls.</li>
    <li>desc_sentence->[PAWN_pronoun] has [PAWN_possessive] eyes closed and looks confident.</li>
    <li>desc_sentence->[PAWN_pronoun] is sleeping, [PAWN_possessive] eyes closed peacefully.</li>
    <li>desc_sentence->[PAWN_pronoun] is smiling with grim joy.</li>
    <li>desc_sentence->[PAWN_pronoun] seems to be fully in control of the situation.</li>
    <li>desc_sentence->There is a flame trail licking off the back of the ship.</li>
    <li>desc_sentence->A nearby [Animal] is looking up, startled.</li>
    <li>desc_sentence->A [Animal] is fleeing the launch in fear.</li>
    <li>desc_sentence->There is a [TerrainFeature] in the background.</li>
    <li>desc_sentence->A [PersonJob] watches silently from afar.</li>
  -->
  <LaunchedShip.rulePack.rulesStrings>
    <li>tale_noun->惑星から脱出する[PAWN_nameDef]</li>
    <li>tale_noun->宇宙へ旅立つ[PAWN_nameDef]</li>
    <li>image->[circumstance_group]宇宙へと打ち上げられる[PAWN_nameDef]</li>
    <li>image->[circumstance_group]天に向かう[PAWN_nameDef]</li>
    <li>image->[circumstance_group]重力圏離脱速度に向けて加速する[PAWN_nameDef]</li>
    <li>image->[circumstance_group]ロケットを操縦する[PAWN_nameDef]</li>
    <li>circumstance_phrase->[TerrainFeature]を前にして</li>
    <li>circumstance_phrase->途方もない力を使って</li>
    <li>circumstance_phrase->塵や岩を吹き飛ばしている中で</li>
    <li>circumstance_phrase->ロケットの劇的な噴射と共に</li>
    <li>circumstance_phrase->正確な離陸をして</li>
    <li>desc_sentence->[PAWN_pronoun]は宇宙船の制御に没頭している｡</li>
    <li>desc_sentence->[PAWN_pronoun]は自信に満ちた様子で目を閉じている｡</li>
    <li>desc_sentence->[PAWN_pronoun]は穏やかに両目を閉じて眠っている｡</li>
    <li>desc_sentence->[PAWN_pronoun]は,薄気味悪い笑みをうかべている.</li>
    <li>desc_sentence->[PAWN_pronoun]は,置かれている状況を完璧に把握しているようだ.</li>
    <li>desc_sentence->宇宙船の後部には噴射流の跡を残している.</li>
    <li>desc_sentence->近くにいる[Animal]はギョッとして見上げている.</li>
    <li>desc_sentence->[Animal]は発射の恐怖で逃げ出している.</li>
    <li>desc_sentence->背景には[TerrainFeature]の姿がある｡</li>
    <li>desc_sentence->[PersonJob]が遠くから無言で眺めている.</li>
  </LaunchedShip.rulePack.rulesStrings>
  
  <!-- EN: social fight -->
  <SocialFight.label>喧嘩</SocialFight.label>
  <!-- EN:
    <li>tale_noun->[INITIATOR_nameDef] [fight_name_present] [RESPONDER_nameDef]</li>
    <li>image->[INITIATOR_nameFull] insulting [RESPONDER_nameFull] [circumstance_group]</li>
    <li>image->[INITIATOR_nameFull] taunting [RESPONDER_nameFull] [circumstance_group]</li>
    <li>image->[INITIATOR_nameFull] threatening [RESPONDER_nameFull] [circumstance_group]</li>
    <li>image->[INITIATOR_nameFull] intimidating [RESPONDER_nameFull] [circumstance_group]</li>
    <li>image->[INITIATOR_nameFull] attacking [RESPONDER_nameFull] [circumstance_group]</li>
    <li>image->[INITIATOR_nameFull] assaulting [RESPONDER_nameFull] [circumstance_group]</li>
    <li>image->[INITIATOR_nameFull] punching [RESPONDER_nameFull] [circumstance_group]</li>
    <li>image->[INITIATOR_nameFull] kicking [RESPONDER_nameFull] [circumstance_group]</li>
    <li>image->[INITIATOR_nameFull] cowering from [RESPONDER_nameFull] [circumstance_group]</li>
    <li>fight_name_present->assaulting</li>
    <li>fight_name_present->attacking</li>
    <li>fight_name_present->fighting</li>
    <li>circumstance_phrase->while [RESPONDER_nameDef] insults [INITIATOR_objective]</li>
    <li>circumstance_phrase->while [RESPONDER_nameDef] taunts [INITIATOR_objective]</li>
    <li>circumstance_phrase->while [RESPONDER_nameDef] threatens [INITIATOR_objective]</li>
    <li>circumstance_phrase->while [RESPONDER_nameDef] intimidates [INITIATOR_objective]</li>
    <li>circumstance_phrase->while [RESPONDER_nameDef] attacks [INITIATOR_objective]</li>
    <li>circumstance_phrase->while [RESPONDER_nameDef] assaults [INITIATOR_objective]</li>
    <li>circumstance_phrase->while [RESPONDER_nameDef] punches [INITIATOR_objective]</li>
    <li>circumstance_phrase->while [RESPONDER_nameDef] kicks [INITIATOR_objective]</li>
    <li>circumstance_phrase->while [RESPONDER_nameDef] cowers from [INITIATOR_objective]</li>
    <li>desc_sentence->[target] appears without remorse.</li>
    <li>desc_sentence->[target] is consumed with passionate rage.</li>
    <li>desc_sentence->[target] has no emotion or expression.</li>
    <li>desc_sentence->[target]'s body is covered in [Gore].</li>
    <li>desc_sentence->[target] is screaming furiously.</li>
    <li>desc_sentence->[target] is visibly wounded.</li>
    <li>desc_sentence->[target]'s eyes are glowing [Color].</li>
    <li>target->[INITIATOR_nameDef]</li>
    <li>target->[RESPONDER_nameDef]</li>
  -->
  <SocialFight.rulePack.rulesStrings>
    <li>tale_noun->[RESPONDER_nameDef][fight_name_present][INITIATOR_nameDef]</li>
    <li>image->[circumstance_group]､[RESPONDER_nameDef]を侮辱する[INITIATOR_nameDef]</li>
    <li>image->[circumstance_group]､[RESPONDER_nameDef]を罵る[INITIATOR_nameDef]</li>
    <li>image->[circumstance_group]､[RESPONDER_nameDef]を脅す[INITIATOR_nameDef]</li>
    <li>image->[circumstance_group]､[RESPONDER_nameDef]を怖がらせる[INITIATOR_nameDef]</li>
    <li>image->[circumstance_group]､[RESPONDER_nameDef]を攻撃する[INITIATOR_nameDef]</li>
    <li>image->[circumstance_group]､[RESPONDER_nameDef]を暴行する[INITIATOR_nameDef]</li>
    <li>image->[circumstance_group]､[RESPONDER_nameDef]を殴る[INITIATOR_nameDef]</li>
    <li>image->[circumstance_group]､[RESPONDER_nameDef]を蹴る[INITIATOR_nameDef]</li>
    <li>image->[circumstance_group]､[RESPONDER_nameDef]を委縮させる[INITIATOR_nameDef]</li>
    <li>fight_name_present->に暴行する</li>
    <li>fight_name_present->を攻撃する</li>
    <li>fight_name_present->と闘う</li>
    <li>circumstance_phrase->[RESPONDER_nameDef]が[INITIATOR_nameDef]を侮辱する一方で</li>
    <li>circumstance_phrase->[RESPONDER_nameDef]が[INITIATOR_nameDef]を罵る一方で</li>
    <li>circumstance_phrase->[RESPONDER_nameDef]が[INITIATOR_nameDef]を脅す一方で</li>
    <li>circumstance_phrase->[RESPONDER_nameDef]が[INITIATOR_nameDef]を怖がらせる一方で</li>
    <li>circumstance_phrase->[RESPONDER_nameDef]が[INITIATOR_nameDef]を攻撃する一方で</li>
    <li>circumstance_phrase->[RESPONDER_nameDef]が[INITIATOR_nameDef]を暴行する一方で</li>
    <li>circumstance_phrase->[RESPONDER_nameDef]が[INITIATOR_nameDef]を殴る一方で</li>
    <li>circumstance_phrase->[RESPONDER_nameDef]が[INITIATOR_nameDef]を蹴る一方で</li>
    <li>circumstance_phrase->[RESPONDER_nameDef]が[INITIATOR_nameDef]を委縮させる一方で</li>
    <li>desc_sentence->[target]に悔恨の念は見えない｡</li>
    <li>desc_sentence->[target]は怒りの矛先を向けられている｡</li>
    <li>desc_sentence->[target]の顔には何の感情も浮かんでいない｡</li>
    <li>desc_sentence->[target]の身体は[Gore]に塗れている｡</li>
    <li>desc_sentence->[target]は怒り狂って叫び声をあげている｡</li>
    <li>desc_sentence->[target]は目に見える程の傷を負っている｡</li>
    <li>desc_sentence->[target]の瞳が[Color]色に染まっている｡</li>
    <li>target->[INITIATOR_nameDef]</li>
    <li>target->[RESPONDER_nameDef]</li>
  </SocialFight.rulePack.rulesStrings>
  
</LanguageData>